data/pie.py
pypastry/__init__.py
pypastry/display.py
pypastry/paths.py
pypastry/commands/__init__.py
pypastry/commands/init.py
pypastry/commands/print_.py
pypastry/commands/run.py
pypastry/experiment/__init__.py
pypastry/experiment/evaluation.py
pypastry/experiment/hasher.py
pypastry/experiment/results.py
pypastry-0.3.0.data/scripts/pastry
pypastry-0.3.0.dist-info/LICENSE
pypastry-0.3.0.dist-info/METADATA
pypastry-0.3.0.dist-info/WHEEL
pypastry-0.3.0.dist-info/entry_points.txt
pypastry-0.3.0.dist-info/top_level.txt
pypastry-0.3.0.dist-info/RECORD
