Metadata-Version: 2.1
Name: pypastry
Version: 0.3.0
Summary: PyPastry machine learning experimentation framework
Home-page: https://github.com/datapastry/pypastry
Author: Daoud Clarke
License: UNKNOWN
Platform: UNKNOWN
Classifier: Programming Language :: Python :: 3.6
Classifier: Programming Language :: Python :: 3.7
Classifier: Programming Language :: Python :: 3.8
Classifier: License :: OSI Approved :: MIT License
Classifier: Operating System :: OS Independent
Requires-Python: >=3.5
License-File: LICENSE
Requires-Dist: tomlkit
Requires-Dist: pandas
Requires-Dist: scikit-learn
Requires-Dist: pyarrow
Requires-Dist: gitpython
Requires-Dist: pytest
